{
  "campaign_id": "v3_finish_pass",
  "phase": "preflight_clean",
  "latest_iteration_id": null,
  "last_successful_gate": null,
  "current_blockers": [],
  "reset_allowed": true,
  "notes": [
    "The active V3 finish pass now targets the corrected 32-experiment matrix described in docs/pilots/v3_gpt_ablations.md.",
    "Legacy March 2026 queue-era iterations under _campaigns/v3_finish_pass/iterations remain historical forensics only.",
    "Use packages/codex:getV3CampaignSnapshot as the primary loop status surface; it combines cohort status with Temporal task-queue readiness."
  ]
}
